a_cv2_imshow_thread/LICENSE
a_cv2_imshow_thread/README.MD
a_cv2_imshow_thread/__init__.py
a_cv2_imshow_thread/requirements.txt
a_cv2_imshow_thread/thirdparty.json
a_cv2_imshow_thread-0.11.dist-info/LICENSE.rst
a_cv2_imshow_thread-0.11.dist-info/METADATA
a_cv2_imshow_thread-0.11.dist-info/WHEEL
a_cv2_imshow_thread-0.11.dist-info/top_level.txt
a_cv2_imshow_thread-0.11.dist-info/RECORD
